pxz/__init__.py
pxz-1.1.14.dist-info/METADATA
pxz-1.1.14.dist-info/WHEEL
pxz-1.1.14.dist-info/top_level.txt
pxz-1.1.14.dist-info/RECORD
