Metadata-Version: 2.2
Name: pxz
Version: 1.1.14
Summary: This Package collects and sends system information.
Author: JPD
Author-email: jpdtester01@gmail.com
License: MIT
Classifier: Programming Language :: Python :: 3
Classifier: License :: OSI Approved :: MIT License
Classifier: Operating System :: OS Independent
Dynamic: author
Dynamic: author-email
Dynamic: classifier
Dynamic: description
Dynamic: description-content-type
Dynamic: license
Dynamic: summary
